PyLights/__init__.py
PyLights/pylights.py
pylights-2.1.dist-info/DESCRIPTION.rst
pylights-2.1.dist-info/METADATA
pylights-2.1.dist-info/RECORD
pylights-2.1.dist-info/WHEEL
pylights-2.1.dist-info/metadata.json
pylights-2.1.dist-info/top_level.txt
