Metadata-Version: 2.0
Name: pylights
Version: 2.1
Summary: Module used to change the color and brightness of lights to the beat of an udio file
Home-page: UNKNOWN
Author: Nickolas Howell
Author-email: nickolas.howell@icloud.com
License: UNKNOWN
Platform: UNKNOWN
Requires-Dist: librosa
Requires-Dist: pygame
Requires-Dist: pyphue
